Metadata-Version: 1.1
Name: win32wifi
Version: 0.0.4
Summary: Python Windows Wifi - !Still Under Development!
Home-page: https://github.com/almondg/win32wifi
Author: Shaked Gitelman
Author-email: shaked.dev@gmail.com
License: GPLv3+
Download-URL: https://github.com/almondg/win32wifi/tarball/0.0.4
Keywords: windows,win32,wifi,wlan,wlanapi,wlanapi.dll
Platform: UNKNOWN
Classifier: Development Status :: 3 - Alpha
Classifier: Intended Audience :: Developers
Classifier: Topic :: Software Development :: Build Tools
Classifier: License :: OSI Approved :: GNU General Public License v3 or later (GPLv3+)
Classifier: Programming Language :: Python :: 3.4
Classifier: Programming Language :: Python :: 3.5
